martscraper/ProductReviewAnalysis.py
martscraper/ProjectVisualisations.py
martscraper/__init__.py
martscraper/amz_comments_scraper.py
martscraper/ecom_prod_scraper.py
martscraper-1.0.1.dist-info/METADATA
martscraper-1.0.1.dist-info/WHEEL
martscraper-1.0.1.dist-info/top_level.txt
martscraper-1.0.1.dist-info/RECORD
